kotobase/__init__.py
kotobase/api.py
kotobase/cli.py
kotobase/core/__init__.py
kotobase/core/datatypes.py
kotobase/db/__init__.py
kotobase/db/database.py
kotobase/db/models.py
kotobase/db_builder/__init__.py
kotobase/db_builder/build_database.py
kotobase/db_builder/config.py
kotobase/db_builder/download.py
kotobase/db_builder/process_jmdict.py
kotobase/db_builder/process_jmnedict.py
kotobase/db_builder/process_kanjidic.py
kotobase/db_builder/process_tatoeba.py
kotobase/db_builder/pull.py
kotobase/db_builder/data/__init__.py
kotobase/db_builder/data/processed/__init__.py
kotobase/db_builder/data/processed/jlpt/__init__.py
kotobase/db_builder/data/processed/jlpt/grammar_n1.json
kotobase/db_builder/data/processed/jlpt/grammar_n2.json
kotobase/db_builder/data/processed/jlpt/grammar_n3.json
kotobase/db_builder/data/processed/jlpt/grammar_n4.json
kotobase/db_builder/data/processed/jlpt/grammar_n5.json
kotobase/db_builder/data/processed/jlpt/kanji_n1.json
kotobase/db_builder/data/processed/jlpt/kanji_n2.json
kotobase/db_builder/data/processed/jlpt/kanji_n3.json
kotobase/db_builder/data/processed/jlpt/kanji_n4.json
kotobase/db_builder/data/processed/jlpt/kanji_n5.json
kotobase/db_builder/data/processed/jlpt/vocab_n1.json
kotobase/db_builder/data/processed/jlpt/vocab_n2.json
kotobase/db_builder/data/processed/jlpt/vocab_n3.json
kotobase/db_builder/data/processed/jlpt/vocab_n4.json
kotobase/db_builder/data/processed/jlpt/vocab_n5.json
kotobase/repos/__init__.py
kotobase/repos/jlpt.py
kotobase/repos/jmdict.py
kotobase/repos/jmnedict.py
kotobase/repos/kanji.py
kotobase/repos/sentences.py
kotobase-0.2.7.dist-info/licenses/LICENSE
kotobase-0.2.7.dist-info/METADATA
kotobase-0.2.7.dist-info/WHEEL
kotobase-0.2.7.dist-info/entry_points.txt
kotobase-0.2.7.dist-info/top_level.txt
kotobase-0.2.7.dist-info/RECORD
