Metadata-Version: 2.4
Name: kotobase
Version: 0.2.7
Summary: Python package for accessing a comprehensive Japanese language database.
Author-email: svdc <svdc1mail@gmail.com>
Maintainer-email: svdc <svdc1mail@gmail.com>
License-Expression: MIT
Project-URL: Homepage, https://github.com/svdC1/kotobase
Project-URL: Issues, https://github.com/svdC1/kotobase/issues
Keywords: Japanese,Dictionary,Language
Classifier: Programming Language :: Python :: 3
Classifier: Operating System :: OS Independent
Classifier: Intended Audience :: Developers
Requires-Python: >=3.9
License-File: LICENSE
Requires-Dist: requests
Requires-Dist: sqlalchemy
Requires-Dist: alembic
Requires-Dist: lxml
Requires-Dist: click
Requires-Dist: gdown
Dynamic: license-file
